iterative_lattice_analysis/__init__.py
iterative_lattice_analysis/iteration_functions.py
iterative_lattice_analysis/support_functions.py
iterative_lattice_analysis/lattice_functions/__init__.py
iterative_lattice_analysis/lattice_functions/crab_cavity.py
iterative_lattice_analysis/lattice_functions/general.py
iterative_lattice_analysis-0.0.1.dist-info/METADATA
iterative_lattice_analysis-0.0.1.dist-info/WHEEL
iterative_lattice_analysis-0.0.1.dist-info/licenses/LICENSE
iterative_lattice_analysis-0.0.1.dist-info/RECORD
