Metadata-Version: 2.4
Name: iterative-lattice-analysis
Version: 0.0.1
Summary: Iterative method for accelerator lattice analysis.
Project-URL: Homepage, https://github.com/anderske-msu/iterative-lattice-analysis
Project-URL: Bug Tracker, https://github.com/anderske-msu/iterative-lattice-analysis/issues
Author-email: Kelly Anderson <kjanderson24@proton.me>
License:                     GNU GENERAL PUBLIC LICENSE
License-File: LICENSE
Classifier: License :: OSI Approved :: GNU General Public License v3 (GPLv3)
Classifier: License :: OSI Approved :: GNU General Public License v3 or later (GPLv3+)
Classifier: Programming Language :: Python :: 3
Classifier: Programming Language :: Python :: 3.10
Classifier: Programming Language :: Python :: 3.11
Requires-Python: >=3.10
Requires-Dist: madx-ptc-utils
Requires-Dist: numpy>=1.2
Requires-Dist: scipy
Requires-Dist: sqrmat-method
Requires-Dist: sympy
